setup.py
shad/__init__.py
shad/base.py
shad.egg-info/PKG-INFO
shad.egg-info/SOURCES.txt
shad.egg-info/dependency_links.txt
shad.egg-info/not-zip-safe
shad.egg-info/requires.txt
shad.egg-info/top_level.txt