Metadata-Version: 1.1
Name: shad
Version: 0.1.5
Summary: Generic restful api -> Python function call adaptor
Home-page: https://bitbucket.org/amjoconn/shad
Author: Albert O'Connor
Author-email: info@albertoconnor.ca
License: MIT
Platform: UNKNOWN
Classifier: Development Status :: 3 - Alpha
Classifier: Intended Audience :: Developers
Classifier: Natural Language :: English
Classifier: Programming Language :: Python
Classifier: Programming Language :: Python :: 2.6
Classifier: Programming Language :: Python :: 2.7
Classifier: Programming Language :: Python :: 3.3
